fastwer.cpython-37m-darwin.so
fastwer-0.1.3.dist-info/LICENSE
fastwer-0.1.3.dist-info/METADATA
fastwer-0.1.3.dist-info/WHEEL
fastwer-0.1.3.dist-info/top_level.txt
fastwer-0.1.3.dist-info/RECORD
