Metadata-Version: 2.1
Name: fastwer
Version: 0.1.3
Summary: A PyPI package for fast word/character error rate (WER/CER) calculation
Home-page: https://github.com/kahne/fastwer
Author: Changhan Wang
Author-email: wangchanghan@gmail.com
License: MIT
Platform: UNKNOWN
Classifier: Intended Audience :: Science/Research
Classifier: Programming Language :: Python :: 3.6
Classifier: Programming Language :: Python :: 3.7
Classifier: Programming Language :: Python :: 3.8
Classifier: Programming Language :: Python :: 3 :: Only
Classifier: Topic :: Scientific/Engineering :: Artificial Intelligence
Requires-Dist: pybind11
